Metadata-Version: 2.4
Name: my_cool_tool_yourname_2
Version: 0.0.1
Summary: A simple calculator example
Author-email: Your Name <your@email.com>
Project-URL: Homepage, https://github.com/yourusername/my_cool_tool
Classifier: Programming Language :: Python :: 3
Classifier: License :: OSI Approved :: MIT License
Classifier: Operating System :: OS Independent
Requires-Python: >=3.7
Requires-Dist: numpy==2.2.0
